{
  "subcommons": [
    {
      "URL": "https://tb.diseasedatahub.org/",
      "name": "TB"
    },
    {
      "URL": "https://aids.diseasedatahub.org/",
      "name": "AIDS"
    },
    {
      "URL": "https://flu.diseasedatahub.org/",
      "name": "FLU"
    },
    {
      "URL": "https://microbiome.diseasedatahub.org/",
      "name": "Microbiome"
    }
  ],
  "gaTrackingId": "UA-119127212-1",
  "graphql": {
    "boardCounts": [
      {
        "graphql": "_subject_count",
        "name": "Subject",
        "plural": "Subjects"
      },
      {
        "graphql": "_study_count",
        "name": "Study",
        "plural": "Studies"
      },
      {
        "graphql": "_summary_lab_result_count",
        "name": "Lab record",
        "plural": "Lab records"
      }
    ],
    "chartCounts": [
      {
        "graphql": "_subject_count",
        "name": "Subject"
      },
      {
        "graphql": "_study_count",
        "name": "Study"
      }
    ],
    "projectDetails": "boardCounts"
  },
  "components": {
    "appName": "Gen3 Disease Data Hub",
    "index": {
      "introduction": {
        "heading": "Gen3 Disease Data Hub Datasets",
        "text": "The Gen3 Disease Data Hub hosts data related to infectious diseases and aims to make data findable, accessible, interoperable, and reusable (FAIR).",
        "link": "/datasets"
      },
      "buttons": [
        {
          "name": "TB Environment",
          "icon": "data-explore",
          "body": "Explore TB data.",
          "external_link": "https://tb.diseasedatahub.org"
        },
        {
          "name": "AIDS Environment",
          "icon": "data-explore",
          "body": "Explore AIDS data.",
          "external_link": "https://aids.diseasedatahub.org"
        },
        {
          "name": "Flu Environment",
          "icon": "data-explore",
          "body": "Explore influenza data.",
          "external_link": "https://flu.diseasedatahub.org"
        },
        {
          "name": "Microbiome Environment",
          "icon": "data-explore",
          "body": "Explore data from a collection of open-access microbiome-related studies.",
          "external_link": "https://microbiome.diseasedatahub.org"
        }
      ]
    },
    "navigation": {
      "items": [
        {
          "icon": "query",
          "link": "/datasets",
          "color": "#a2a2a2",
          "name": "Dataset Browser"
        },
        {
          "icon": "exploration",
          "link": "/explorer",
          "color": "#a2a2a2",
          "name": "Eco Explorer"
        }
      ]
    },
    "topBar": {
      "items": [
        {
          "link": "https://gen3.org/resources/user/",
          "name": "Documentation"
        }
      ]
    },
    "login": {
      "title": "Gen3 Disease Data Hub",
      "subTitle": "Cross Environment Datasets",
      "text": "The website combines open access datasets from multiple disciplines to create clean, easy to navigate visualizations for data-driven discovery within the fields of allergy and infectious diseases.",
      "contact": "If you have any questions about access or the registration process, please contact ",
      "email": "support@gen3.org"
    },
    "footerLogos": [
      {
        "src": "/custom/sponsors/gitops-sponsors/gen3.png",
        "href": "https://ctds.uchicago.edu/gen3",
        "alt": "Gen3 Data Commons"
      },
      {
        "src": "/src/img/createdby.png",
        "href": "https://ctds.uchicago.edu/",
        "alt": "Center for Translational Data Science at the University of Chicago"
      }
    ]
  },
  "requiredCerts": [],
  "featureFlags": {
    "explorer": true,
    "analysis": true
  },
  "datasetBrowserConfig": {
    "filterSections": [
      {
        "title": "Supported Data Resources",
        "options": [
          { "text": "TB", "filterType": "singleSelect"},
          { "text": "AIDS", "filterType": "singleSelect"},
          { "text": "Flu", "filterType": "singleSelect"},
          { "text": "Microbiome", "filterType": "singleSelect"}
        ]
      },
      {
        "title": "Research Focus",
        "options": [
          { "text": "AIDS", "filterType": "singleSelect"},
          { "text": "TB", "filterType": "singleSelect"},
          { "text": "Flu", "filterType": "singleSelect"},
          { "text": "Immune Response", "filterType": "singleSelect"},
          { "text": "Immune Phenotype", "filterType": "singleSelect"},
          { "text": "Allergy", "filterType": "singleSelect"},
          { "text": "Atopy", "filterType": "singleSelect"},
          { "text": "Infection Response", "filterType": "singleSelect"},
          { "text": "Vaccine Response", "filterType": "singleSelect"},
          { "text": "Transplantation", "filterType": "singleSelect"},
          { "text": "Oncology", "filterType": "singleSelect"},
          { "text": "Autoimmune", "filterType": "singleSelect"},
          { "text": "Preterm Birth", "filterType": "singleSelect"}
        ]
      }
    ],
    "fieldMapping" : [
      { "field": "link", "name": "View" },
      { "field": "dataset_name", "name": "Study" },
      { "field": "supported_data_resource", "name": "Supported Data Resource" },
      { "field": "research_focus", "name": "Research Focus" },
      { "field": "description", "name": "Description of Dataset" }
    ],
    "filterConfig": {
      "tabs": [{
        "title": "Filters",
        "fields": ["supported_data_resource", "research_focus"]
      }]
    }
  },
  "dataExplorerConfig": {
    "charts": {
      "project_id": {
        "chartType": "count",
        "title": "Projects"
      },
      "subject_id": {
        "chartType": "count",
        "title": "Subjects"
      },
      "dataset": {
        "chartType": "pie",
        "title": "Resources",
        "chartRow": 0
      },
      "data_format": {
        "chartType": "bar",
        "title": "Data Format",
        "chartRow": 0
      },
      "data_type": {
        "chartType": "pie",
        "title": "Data Type",
        "chartRow": 0
      },
      "experimental_strategies": {
        "chartType": "bar",
        "title": "Experimental Strategies",
        "chartRow": 0
      },
      "species": {
        "chartType": "bar",
        "title": "Genus species",
        "chartRow": 0
      },
      "gender": {
        "chartType": "pie",
        "title": "Gender",
        "chartRow": 1
      },
      "race": {
        "chartType": "pie",
        "title": "Race",
        "chartRow": 1
      },
      "ethnicity": {
        "chartType": "pie",
        "title": "Ethnicity",
        "chartRow": 1
      },
      "biospecimen_anatomic_site": {
        "chartType": "pie",
        "title": "Biospecimen Anatomic Site",
        "chartRow": 1
      }
    },
    "fieldMapping" : [
      { "field": "dataset", "name": "Resource" },
      { "field": "studyAccession", "name": "Study" },
      { "field": "phenotype", "name": "Phenotype" },
      { "field": "gender", "name": "Gender" },
      { "field": "ethnicity", "name": "Ethnicity" },
      { "field": "strain", "name": "Strain" },
      { "field": "species", "name": "Genus species" },
      { "field": "submitter_id", "name": "Submitter ID" },
      { "field": "race", "name": "Race" },
      { "field": "hiv_status", "name": "HIV Status" },
      { "field": "study_submitter_id", "name": "Study"},
      { "field": "frstdthd", "name": "Year of Death" },
      { "field": "arthxbase", "name": "ART Use Prior to Baseline"},
      { "field": "bshbvstat", "name": "Baseline HBV Sero-status"},
      { "field": "bshcvstat", "name": "Baseline HCV Sero-status"},
      { "field": "cd4nadir", "name": "CD4 Nadir Prior to HAART"},
      { "field": "status", "name": "Summarized HIV Sero-status"},
      {"field": "project_id", "name": "Project ID"},
      {"field": "frstcncrd", "name": "First Confirmed Cancer Year"},
      {"field": "frstdmd", "name": "First Visit Year with Diabetes"},
      {"field": "frstdmmd", "name": "First Visit Year with All Necessary Components to Determine Diabetes"},
      {"field": "frsthtnd", "name": "First Visit Year with Hypertension"},
      {"field": "frsthtnmd", "name": "First Visit Year with All Necessary Components to Determine Hypertension"},
      {"field": "fcd4lowd", "name": "First Year Seen CD4N < 200 or CD4% < 14"},
      {"field": "fposdate", "name": "First Year Seen Seropositive"},
      {"field": "frstaidd", "name": "First Reported AIDS Year"},
      {"field": "lastafrd", "name": "Last Reported AIDS Free Year"},
      {"field": "lastcond", "name": "Year of Last Study Visit Attended"},
      {"field": "lastcontact", "name": "Last Year of Contact"},
      {"field": "lcd4higd", "name": "Last Year Seen with CD4N >= 200 and CD4% >= 14"},
      {"field": "lnegdate", "name": "Last Year Seen Seronegative"},
      {"field": "amikacin_res_phenotype", "name": "Amikacin Phenotype" },
      {"field": "capreomycin_res_phenotype", "name": "Capreomycin Phenotype" },
      {"field": "isoniazid_res_phenotype", "name": "Isoniazid Phenotype" },
      {"field": "kanamycin_res_phenotype", "name": "Kanamycin Phenotype" },
      {"field": "ofloxacin_res_phenotype", "name": "Ofloxacin Phenotype" },
      {"field": "pyrazinamide_res_phenotype", "name": "Pyrazinamide Phenotype" },
      {"field": "rifampicin_res_phenotype", "name": "Rifampicin Phenotype" },
      {"field": "rifampin_res_phenotype", "name": "Rifampin Phenotype" },
      {"field": "streptomycin_res_phenotype", "name": "streptomycin Phenotype" }
    ],
    "filterConfig": {
      "tabs": [{
        "title": "Resource",
        "fields": ["dataset", "data_format", "data_type"]
      },
      {
        "title": "Subject",
        "fields": ["ethnicity", "gender", "species", "race"]
      },
      {
        "title": "Diagnosis",
        "fields": [
          "arthxbase",
          "bshbvstat",
          "bshcvstat",
          "cd4nadir",
          "status",
          "hiv_status"
        ]
      },
      {
        "title": "Comorbidity",
        "fields": [
          "frstcncrd",
          "frstdmd",
          "frstdmmd",
          "frsthtnd",
          "frsthtnmd"
        ]
      }, {
        "title": "HIV History",
        "fields": [
          "cd4nadir",
          "fcd4lowd",
          "fposdate",
          "frstaidd",
          "lastafrd",
          "lastcond",
          "lastcontact",
          "lcd4higd",
          "lnegdate",
          "status"
        ]
      },
      {
        "title": "Drug Resistance",
        "fields": [
          "amikacin_res_phenotype",
          "capreomycin_res_phenotype",
          "isoniazid_res_phenotype",
          "kanamycin_res_phenotype",
          "ofloxacin_res_phenotype",
          "pyrazinamide_res_phenotype",
          "rifampicin_res_phenotype",
          "rifampin_res_phenotype",
          "streptomycin_res_phenotype"
        ]
      },
      {
        "title": "Experiment",
        "fields": [
          "experimental_strategies",
          "virus_type",
          "virus_subtype",
          "analyte_type",
          "biospecimen_anatomic_site",
          "cell_line",
          "sample_type",
          "composition",
          "strain"
        ]
      }]
    }
  }
}
